pesic/__init__.py
pesic/api.py
pesic/const.py
pesic/custom_exceptions.py
pesic-0.3.0.dist-info/LICENSE
pesic-0.3.0.dist-info/METADATA
pesic-0.3.0.dist-info/WHEEL
pesic-0.3.0.dist-info/top_level.txt
pesic-0.3.0.dist-info/RECORD
