Metadata-Version: 2.1
Name: pesic
Version: 0.3.0
Summary: PetroElectroSbyt API Wrapper
Home-page: https://github.com/StanislavBolshakov/pesic
Author: Stanislav Bolshakov
Author-email: st.bolshakov@gmail.com
Classifier: Development Status :: 3 - Alpha
Classifier: License :: OSI Approved :: Apache Software License
Classifier: Programming Language :: Python :: 3
Classifier: Operating System :: OS Independent
Requires-Python: >=3.8
License-File: LICENSE
Requires-Dist: aiohttp
Requires-Dist: asyncio
